README.md
README.rst
setup.py
hrf_opt/__init__.py
hrf_opt/__main__.py
hrf_opt/find_opt_hrf.py
hrf_opt/hrf_opt_main.py
hrf_opt/hrf_opt_utils.py
hrf_opt/load_config.py
hrf_opt.egg-info/PKG-INFO
hrf_opt.egg-info/SOURCES.txt
hrf_opt.egg-info/dependency_links.txt
hrf_opt.egg-info/entry_points.txt
hrf_opt.egg-info/requires.txt
hrf_opt.egg-info/top_level.txt