Metadata-Version: 1.0
Name: hrf-opt
Version: 1.0.1
Summary: Optimize hemodynamic response function parameters.
Home-page: https://github.com/MSchnei/hrf_opt
Author: Marian Schneider
Author-email: marian.schneider@maastrichtuniversity.nl
License: GNU General Public License Version 3
Keywords: pRF,fMRI,retinotopy
Platform: UNKNOWN
